Workbook
Name ADDRESS: Master!#REF!
Name CC: Master!$M:$M
Name CD: Master!#REF!
Name CITY: Master!#REF!
Name CLIENT: Master!$A:$A
Name CONTACT_2: Master!$AC:$AC
Name COUNTY: Master!#REF!
Name EQUIP: Master!$B:$B
Name INSTALL: Master!#REF!
Name LICENSE: Master!#REF!
Name NAME: Master!$P:$P
Name PHONE: Master!$Q:$Q
Name PHONE_2: Master!$AD:$AD
Name REC: Master!#REF!
Name REM: Master!#REF!
Name STATE: Master!$X:$X
Name TERMS: Master!#REF!
Name VERS: Master!#REF!
Name ZIP: Master!$Y:$Y

Sheet New Client
B2: #VALUE! | J2: Invoice No:
C4: 101 Glacier Point, Suite B | J4: Date:
C5: San Rafael, Ca 94901 | J5: TERMS:
C6: 415-451-4861 | E6: admin@performancepos.com | J6: Ordered by:
J7: Rep:
A9: ************************************************ | C9: ************************************ | F9: INVOICE | J9: *******************************
B11: Bill To | I11: Deliver To
B12: Client:
B13: c/o
B14: Address:
B15: City:
B16: Phone:
B17: Email:
C19: Products:
B20: Qty: | E20: Description: | J20: Unit Price | K20: Total
K21: =B21*J21 -> 0
K22: =B22*J22 -> 0
K23: =B23*J23 -> 0
K24: =B24*J24 -> 0
K25: =B25*J25 -> 0
K26: =B26*J26 -> 0
K27: =B27*J27 -> 0
I28: Taxable Subtotal: | K28: =SUM(K21:K27) -> 0
I29: Shipping
I30: Sales Tax | K30: =K28*J30 -> 0
C31: Services:
B32: Unit | E32: Description: | J32: Rate
K33: =J33*B33 -> 0
K34: =B34*J34 -> 0
K35: =B35*J35 -> 0
K36: =B36*J36 -> 0
K37: =B37*J37 -> 0
K38: =B38*J38 -> 0
J39: travel
C41: Payment Details
J42: TOTAL: | K42: =SUM(K28:K39) -> 0
J44: office use only:
C48: I agree to the above charges and to pay this invoice according to the stated terms
C50: Client Signature
D52: This is your invoice. Kindly Pay from this invoice

Sheet Invoice
J2: Invoice No: | K2: 12315805
C4: 101 Glacier Point, Suite B | J4: Date: | K4: 46022
C5: San Rafael, Ca 94901 | J5: TERMS: | K5: Net30
C6: 415-451-4861 | E6: admin@performancepos.com | J6: Ordered by:
J7: Rep: | K7: Antonio Hudnall
A8: ************************************************ | C8: ************************************ | F8: INVOICE | J8: *******************************
B9: Bill To | I9: Deliver To
B10: Client: | C10: El Quetzal Deli | I10: =C10 -> El Quetzal Deli
B11: c/o | C11: =LOOKUP(C10,Master!A:A,Master!AT:AT) -> 0
B12: Address: | C12: =LOOKUP(C10,Master!A:A,Master!AU:AU) -> 136 Bellam Boulevard | I12: =LOOKUP(C10,Master!A:A,Master!T:T) -> 136 Bellam Boulevard
B13: City: | C13: =LOOKUP(C10,Master!A:A,Master!AW:AW) -> San Rafael | E13: =LOOKUP(C10,Master!A:A,Master!AX:AX) -> Ca | F13: =LOOKUP(C10,Master!A:A,Master!AY:AY) -> 94901 | I13: =LOOKUP(C10,Master!A:A,Master!U:U) -> San Rafael | J13: =LOOKUP(C10,Master!A:A,Master!V:V) -> Ca | K13: =LOOKUP(C10,Master!A:A,Master!W:W) -> 94901
B14: Phone: | C14: =LOOKUP(C10,Master!A:A,Master!AZ:AZ) -> 415-259-7333 | I14: =LOOKUP(C10,Master!A:A,Master!O:O) -> 415-654-6312
B15: Email:
C17: Products:
B18: Qty: | E18: Description: | J18: Unit Price | K18: Total
K20: =B20*J20 -> 0
K21: =B21*J21 -> 0
K23: =B23*J23 -> 0
K24: =B24*J24 -> 0
K25: =B25*J25 -> 0
K26: =B26*J26 -> 0
I27: Taxable Subtotal: | K27: =SUM(K19:K26) -> 0
B28: =LOOKUP(C10,Master!A:A,Master!S:S) -> SR | I28: Shipping
I29: Sales Tax | J29: =LOOKUP(C10,Master!A:A,Master!Q:Q) -> 0.095 | K29: =K27*J29 -> 0
C30: Services:
B31: Unit | E31: Description: | J31: Rate
K32: =J32*B32 -> 0
K34: =B34*J34 -> 0
K35: =B35*J35 -> 0
K36: =B36*J36 -> 0
K37: =B37*J37 -> 0
J38: travel
C40: Payment Details
J41: TOTAL: | K41: =SUM(K27:K38) -> 0
J43: office use only:
C47: I agree to the above charges and to pay this invoice according to the stated terms
C49: Client Signature
D51: This is your invoice. Kindly Pay from this invoice

Sheet Master
A1: 46022 | B1: SYSTEM | E1: HELP DESK | H1: HW MAINT | K1: REVENUE TRACKING | N1: PRIMARY CONTACT | Q1: TAX% | R1: Tax % | S1: Tax Dist | T1: STORE ADDRESS | X1: Ops Email | Y1: Billing Email | Z1: Other Email | AA1: CONTACT #2 | AC1: CONTACT #3 | AE1: CONTACT #4 | AG1: CONTACT #5 | AI1: FAX | AK1: website | AL1: Paper #1 | AM1: Paper #2 | AN1: Paper #3 | AO1: Ribbon #1 | AP1: Ribbon #2 | AQ1: Label/Other | AR1: Other | AT1: Bill To Name | AU1: Street | AW1: City | AX1: St | AY1: Zip | AZ1: Phone
B2: type | C2: AM | D2: WS | E2: y/n ? | G2: $$ | H2: y/n ? | I2: exp | J2: $$ | K2: LAST SUPPLY?? | M2: LAST T&M ?? | N2: Name | O2: Phone | P2: Cell | T2: STREET | U2: CITY | V2: ST | W2: ZIP | AA2: Name | AB2: Phone | AC2: Name | AD2: Phone | AE2: Name | AF2: Phone | AG2: Name | AH2: Phone | AI2: Store | AJ2: Corp or A/P | AL2: Supply Info | AT2: Billing Info
A3: 16th Street Taco | B3: SUPPLY ONLY | C3: AH | E3: NO | H3: NO | M3: 44532 | N3: Eduardo Jaurez | O3: 415-725-0715 | Q3: 0.08625 | S3: SF | T3: 980 16th Street | U3: San Francisco | V3: Ca | W3: 94107 | AU3: 980 16th Street | AW3: San Francisco | AX3: Ca | AY3: 94107 | AZ3: 415-725-0715
A4: 2 Star Market | B4: CASIO | C4: LG | D4: Qt-6600 | E4: NO | H4: NO | M4: 43927 | N4: Ali | O4: 510-531-3576 | Q4: 0.1025 | S4: ALA | T4: 2020 MacArthur Blvd | U4: Oakland | V4: Ca | W4: 94602 | AU4: 2020 MacArthur Blvd | AW4: Oakland | AX4: Ca | AY4: 94602 | AZ4: 510-531-3576
A5: 22nd & Irving Market | B5: SCALE | C5: RA | D5: LP-1000 | E5: NO | H5: NO | K5: 45356 | M5: 44180 | N5: Chris | O5: 415-681-5212 | Q5: 0.08625 | S5: SF | T5: 2101 Irving Street | U5: San Francisco | V5: Ca | W5: 94122 | AQ5: 1493 | AU5: 2101 Irving Street | AW5: San Francisco | AX5: Ca | AY5: 94122 | AZ5: 415-681-5212
A6: 26 Mix | B6: ECR | C6: AH | D6: Sam4s ER945 raised | E6: NO | H6: NO | K6: 44358 | M6: 44449 | N6: William Mayorga | O6: 415-826-7378 | P6: 510-734-5931 | Q6: 0.08625 | R6: 0.0875 | S6: SF | T6: 3024 Mission Street | U6: San Francisco | V6: Ca | W6: 94110 | AU6: 3024 Mission Street | AW6: San Francisco | AX6: Ca | AY6: 94110 | AZ6: 415-826-7378
A7: 3 Star Food & Liquor | B7: CASIO | C7: LG | D7: Casio TE7000 | E7: NO | H7: NO | M7: 43026 | N7: Mandeep | O7: 510-340-1366 | Q7: 0.0975 | R7: 0.085 | S7: Concord | T7: 1140 Meadow Lane | U7: Concord | V7: Ca | W7: 94520 | AA7: Dependu | AU7: 1140 Meadow Lane | AW7: Concord | AX7: Ca | AY7: 94520 | AZ7: 510-340-1366
A8: 420 Smoke Palace **c.o.d. prepay** | B8: ECR | C8: AH | D8: Sam4s SAP-630 | E8: NO | F8: *COD/PREPAY ONLY** | H8: NO | I8: *COD/PREPAY ONLY** | K8: 43878 | M8: 44568 | N8: Abassi | O8: 408-880-4200 | Q8: 0.09375 | S8: SanJose | T8: 396 S. Bascom Avenue | U8: San Jose | V8: Ca | W8: 95128 | AL8: 54-230 | AU8: 396 S. Bacom Avenue | AW8: San Jose | AX8: Ca | AY8: 95128 | AZ8: 408-880-4200
A9: 5th Street Steakhouse | B9: SUPPLY ONLY | C9: AH | E9: NO | H9: NO | K9: 45968 | N9: Traci | O9: 530-891-6328 | Q9: 0.0925 | R9: 0.075 | S9: BUTTE | T9: 345 W. 5th Street | U9: Chico | V9: Ca | W9: 95928 | X9: wearschico@yahoo.com | Y9: wearschico@yahoo.com | AA9: Angela | AI9: 530-891-8339 | AL9: 54-230 | AM9: 13305 | AN9: 15741 | AO9: 62245 | AP9: 62235 | AU9: 345 W. 5th Street | AW9: Chico | AX9: Ca | AY9: 95928 | AZ9: 530-891-6328
A10: 65th Street Market | B10: ECR | C10: AH | D10: Sam4s ER260 | E10: NO | H10: NO | K10: 45881 | M10: 44249 | N10: Murshed Adbul | O10: 510-655-6838 | Q10: 0.105 | S10: Emery | T10: 6444 San Pablo Ave | U10: Emeryville | V10: Ca | W10: 94608 | AL10: 15157 | AU10: 6444 San Pablo Ave | AW10: Emeryville | AX10: Ca | AY10: 94608 | AZ10: 510-655-6838
A11: 76 Auto Care Service | B11: SUPPLY ONLY | C11: AH | E11: NO | H11: NO | K11: 43544 | N11: Babu | O11: 510-530-5605 | Q11: 0.1025 | S11: ALA | T11: 4500 Park Blvd | U11: Oakland | V11: Ca | W11: 94602 | AL11: 54-230 | AM11: 15153 | AU11: 4500 Park Blvd | AW11: Oakland | AX11: Ca | AY11: 94602 | AZ11: 510-530-5605
A12: 88 Sushi & Ramen | B12: SUPPLY ONLY | C12: AH | E12: 7 X 24 | F12: SpotOn | H12: NO | K12: 45197 | N12: J. Decastro | O12: 650-948-8388 | Q12: 0.0913 | S12: SC | T12: 530 Showers Drive. #4 | U12: Mountain View | V12: Ca | W12: 94040 | AL12: 15-741 | AU12: 530 Showers Drive, #4 | AW12: Mountain View | AX12: Ca | AY12: 94040 | AZ12: 650-948-8388
A13: 9th Street Market | B13: ECR | C13: AH | D13: Sam4s ER945 raised | E13: NO | H13: NO | K13: 44188 | M13: 44188 | N13: Nav Singh | O13: 707-542-5903 | P13: 559-260-5848 cell | Q13: 0.1 | S13: S.Rosa | T13: 766 Wilson Street | U13: Santa Rosa | V13: Ca | W13: 95401 | X13: mail4navsingh.nps@gmail.com | Y13: mail4navsingh.nps@gmail.com | Z13: mail4navsingh.nps@gmail.com | AL13: 15157 | AU13: 766 Wilson Street | AW13: Santa Rosa | AX13: Ca | AY13: 95401 | AZ13: 707-542-5903
A14: a Mano | B14: SUPPLY ONLY | C14: AH | E14: NO | H14: NO | K14: 44950 | M14: 44573 | N14: Rodrigo | O14: 415-506-7401 | P14: 415-271-3947 | Q14: 0.08625 | S14: SF | T14: 450 Hayes Street | U14: San Francisco | V14: Ca | W14: 94102 | X14: info@amanosf.com | Y14: iberdougo@backofthehouseinc.com | Z14: rodrigo@backofthehouseinc.com | AI14: 415-506-7401 | AL14: 54-230 | AM14: 13305 | AN14: CC235 | AO14: 62245 | AU14: 450 Hayes St | AW14: San Francisco | AX14: Ca | AY14: 94102 | AZ14: 415-881-7020
A15: A Sweet Affair - California | B15: SpotOn | C15: RA | E15: NO | H15: NO | M15: 43859 | N15: Terry Babcock | O15: 925-943-2253 | P15: 925-785-5931 | Q15: 0.0925 | R15: 0.085 | S15: CC | T15: 1991 N California Blvd | U15: Walnut Creek | V15: Ca | W15: 94598 | X15: asweetaffairbakery@usa.com | Y15: idreamofaruba@gmail.com | Z15: idreamofaruba@gmail.com | AA15: Sarah Torres -> | AB15: 925-395-1695 | AC15: EMAIL IDREAM | AU15: 1991 N California Blvd | AW15: Walnut Creek | AX15: Ca | AY15: 94598 | AZ15: 925-785-5931
A16: A Sweet Affair - Ygnacio | B16: SpotOn | C16: RA | E16: 7 X 24 | F16: SpotOn | M16: 44372 | N16: Terry Babcock | O16: 925-944-1910 | Q16: 0.0925 | R16: 0.085 | S16: CC | T16: 1815 Ygnacio Valley Road Ste F | U16: Walnut Creek | V16: Ca | W16: 94598 | X16: bakerhot1@aol.com | Y16: idreamofaruba@gmail.com | Z16: idreamofaruba@gmail.com | AA16: Terry-owner | AB16: 925-785-5931 | AI16: 925-947-6000 | AU16: 1815 Ygnacio Valley Road Ste F | AW16: Walnut Creek | AX16: Ca | AY16: 94598 | AZ16: 925-944-1910
A17: A&W - San Rafael | B17: BRINK | C17: MB | E17: M-F | F17: 45519 | G17: 49 | H17: NO | K17: 43747 | M17: 45762 | N17: David | O17: 415-479-9652 | P17: .; | Q17: 0.0925 | S17: SR | T17: 3741 Redwood Highway | U17: San Rafael | V17: Ca | W17: 94903 | X17: bigbromberger@gmail.com | Y17: brombergerville@hotmail.com | AL17: 15303 | AU17: 3741 Redwood Highway | AW17: San Rafael | AX17: Ca | AY17: 94903 | AZ17: 415-479-9652
A18: Ace Wasabi | B18: SUPPLY ONLY | C18: AH | K18: 44798 | N18: Ken Lowe | O18: 415-567-4903 | P18: 415-819-8477 | Q18: 0.08625 | R18: 0.0875 | S18: SF | T18: 3339 Steiner Street | U18: San Francisco | V18: Ca | W18: 94123 | X18: klowe1414@yahoo.com | Y18: klowe1234@gmail.com | AA18: vicas | AB18: 415-850-7530 | AI18: 415-749-1873 | AL18: 54-230 | AM18: 13305 | AO18: 67240 | AU18: 3339 Steiner Street | AV18: 3339 STEINER STREET | AW18: San Francisco | AX18: Ca | AY18: 94123 | AZ18: 415-576-4903
A19: Achilles by the Sea | B19: SPOT ON | C19: AH | E19: 7 X 24 | F19: SpotOn | K19: 45527 | N19: Diaa Atali | O19: 650-476-6663 | P19: 650-476-6663 | Q19: 0.0925 | S19: S.Cruz | T19: 1404 Soquel Ave | U19: Santa Cruz | V19: Ca | W19: 95062 | X19: achillessantaclara@gmail.com | Y19: achillessantaclara@gmail.com | Z19: achillessantaclara@gmail.com | AL19: 54-230 | AM19: 13305 | AO19: 62245 | AU19: 1404 Soquel Ave | AW19: Santa Cruz | AX19: Ca | AY19: 95062 | AZ19: 650-476-6663
A20: Acre Restaurant | B20: Spot On | C20: DK | E20: Spot On | H20: NO | K20: 45999 | M20: 45309 | N20: Dirk/Kirsten | Q20: 0.1025 | S20: ALA | T20: 5655 College Ave | U20: Oakland | V20: Ca | W20: 94618 | X20: kirsten@acre-restaurant.com | Y20: kirsten@acre-restaurant.com | Z20: kirsten@acre-restaurant.com | AL20: 54230 | AM20: 13305 | AN20: cc235 | AO20: 62245 | AQ20: 15741 | AU20: 5655 College Ave | AW20: Oakland | AX20: Ca | AY20: 94618
A21: Agave - Healdsburg | B21: SUPPLY ONLY | C21: AH | E21: NO | H21: NO | M21: 44403 | N21: Octavio Diaz | O21: 707-433-2411 | Q21: 0.0975 | S21: Heald | T21: 1063 Vine St | U21: Healdsburg | V21: Ca | W21: 95448 | X21: daisy@merlobiz.com | Y21: mail@merlobiz.com | Z21: tishia@merlobiz.com | AU21: 1063 Vine St | AW21: Healdsburg | AX21: Ca | AY21: 95448 | AZ21: 707-433-2411
A22: Aguachiles El Tamarindo | B22: NCC | C22: LG | E22: NO | H22: NO | M22: 45110 | N22: Edgar | O22: 510-500-7552 | P22: 510-393-2242 cell | Q22: 0.1025 | S22: ALA | T22: 3053 International Blvd | U22: Oakland | V22: Ca | W22: 94601 | Y22: eg333366@gmail.com | AU22: 3053 International Blvd | AW22: Oakland | AX22: Ca | AY22: 94601 | AZ22: 510-500-7552
A23: Alana's - Burlingame | B23: NCC | C23: LG | E23: 7 X 24 | F23: 45505 | G23: 49 | H23: DEPOT | I23: 45505 | J23: 39 | K23: 45887 | M23: 45855 | N23: Francesca | O23: 650-348-0417 | P23: 650-799-9230 | Q23: 0.09625 | R23: 0.09 | S23: Burl | T23: 1408 Burlingame Avenue | U23: Burlingame | V23: Ca | W23: 94010 | X23: info@alanascafe.com | Y23: francesca@alanascafe.com | AA23: Teresa | AC23: Tim | AD23: 650-703-9981 | AL23: 54-230 | AN23: CC235 | AO23: 62245 | AU23: =PROPER(AV23) -> 1408 Burlingame Avenue | AV23: 1408 BURLINGAME AVENUE | AW23: Burlingame | AX23: Ca | AY23: 94010 | AZ23: 650-348-0417
A24: Alegria's | B24: SUPPLY ONLY | C24: AH | E24: NO | H24: NO | K24: 43077 | M24: 43668 | N24: Angelynne | O24: 415-929-8888 | Q24: 0.08625 | R24: 0.0875 | S24: SF | T24: 2018 Lombard Street | U24: San Francisco | V24: Ca | W24: 94123 | X24: info@alegraissf.com | AA24: Arman | AM24: CC235 | AO24: 62245 | AU24: =PROPER(AV24) -> 2018 Lombard Street | AV24: 2018 LOMBARD STREET | AW24: San Francisco | AX24: Ca | AY24: 94123 | AZ24: 415-929-8888
A25: Alejandro's Taqueria - Fairfield | B25: ECR | C25: AH | D25: Sam ER940 flat | E25: NO | H25: NO | K25: 45215 | M25: 42929 | N25: Lety | O25: 707-429-2155 | Q25: 0.08375 | S25: SOL | T25: 936 Texas Street | U25: Fairfield | V25: Ca | W25: 94533 | AL25: 15157 | AM25: 44150 | AO25: 67655 | AU25: 936 Texas Street | AW25: Fairfield | AX25: Ca | AY25: 94533 | AZ25: 707-429-2155
A26: Alejandro's Taqueria - Sacramento | B26: ECR | C26: AH | D26: Sam ER940 flat | E26: NO | H26: NO | M26: 43581 | N26: Luis | O26: 916-459-0924 | Q26: 0.0875 | S26: SacCity | T26: 911 K Street | U26: Sacramento | V26: Ca | W26: 95814 | X26: lbarr@sbcglobal.net | Z26: lbarr@sbcglobal.net | AL26: 15157 | AU26: 911 K Street | AW26: Sacramento | AX26: Ca | AY26: 95814 | AZ26: 916-459-0924
A27: All Star Donut | B27: ECR | C27: AH | D27: SAM 260 | E27: NO | H27: NO | M27: 44858 | N27: Sem | O27: 510-525-7289 | Q27: 0.1025 | R27: 0.095 | S27: El Cerr | T27: 3070 El Cerrito Plaza | U27: El Cerrito | V27: Ca | W27: 94530 | AU27: 3070 El Cerrito Plaza | AW27: El Cerrito | AX27: Ca | AY27: 94530 | AZ27: 510-525-7289
A28: Alley & Vine | B28: SUPPLY ONLY | C28: AH | E28: NO | H28: NO | K28: 45257 | N28: Ricardo | O28: 510-227-5006 | Q28: 0.1075 | S28: ALA | T28: 1332 Park St Suite D | U28: Alameda | V28: Ca | W28: 94501 | AL28: 54-230 | AM28: 15741 | AN28: CC235 | AU28: 1332 Park St Suite D | AW28: Alameda | AX28: Ca | AY28: 94501 | AZ28: 510-227-5006
A29: Alotta's Deli & Catering | B29: NCC | C29: RA | E29: *** COD/ Prepay only ONLY ** | H29: NO | M29: 45721 | N29: Mike Mansch | O29: 650-967-0299 | P29: 408-807-0575 | Q29: 0.0925 | S29: LosAltos | T29: 2249 Grant Road | U29: Los Altos | V29: Ca | W29: 94024 | X29: alottasdeli@aol.com | Y29: alottasdeli@aol.com | Z29: alottasdeli@aol.com | AU29: 2249 Grant Road | AW29: Los Altos | AX29: Ca | AY29: 94024 | AZ29: 650-967-0299
A30: Amakara | B30: SUPPLY ONLY | C30: AH | E30: NO | H30: NO | K30: 46003 | M30: 43032 | N30: Myly | O30: 925-803-8485 | P30: 925-992-9819 | Q30: 0.1025 | R30: 0.095 | S30: ALA | T30: 7568 Dublin Blvd | U30: Dublin | V30: Ca | W30: 94568 | X30: amakaracompany@gmail.com | AA30: Eddie (owner) | AB30: 209-601-8923 | AC30: Tae Oh | AD30: 408-981-6142 | AL30: 54-230 | AM30: 13305 | AN30: CC235 | AO30: 62245 | AU30: 7568 Dublin Blvd | AV30: 7222 REGIONAL STREET | AW30: Dublin | AX30: Ca | AY30: 94568 | AZ30: 925-803-8485
A31: Amal's Deli | B31: NCC | C31: RA | E31: NO | H31: NO | M31: 44776 | N31: Rana | O31: 415-227-3797 | Q31: 0.08625 | S31: SF | T31: 1416 Haight St | U31: San Francisco | V31: Ca | W31: 94117 | AU31: 1416 Haight St | AW31: San Francisco | AX31: Ca | AY31: 94117 | AZ31: 415-227-3797
A32: American Bull | B32: NCC | C32: RA | E32: NO | H32: NO | K32: 43363 | M32: 43955 | N32: Liz Jones | O32: 650-652-4908 | P32: 650-504-3947 | Q32: 0.09625 | R32: 0.09 | S32: Burl | T32: 1819 El Camino Real | U32: Burlingame | V32: Ca | W32: 94010 | X32: theamericanbullbarandgrill@gmail.com | AA32: Daniel (Liz's son) | AB32: 650-504-3945 | AI32: 650-652-9825 | AL32: 54-230 | AM32: 13305 | AO32: 62245 | AU32: =PROPER(AV32) -> 1819 El Camino Real | AV32: 1819 EL CAMINO REAL | AW32: Burlingame | AX32: Ca | AY32: 94010 | AZ32: 650-652-4908
A33: Anaheim White House | B33: SUPPLY ONLY | C33: AH | E33: NO | H33: NO | K33: 45939 | N33: Sylvano | O33: 714-772-1381 | Q33: 0.0775 | S33: OC | T33: 887 S. Anaheim Blvd | U33: Anaheim | V33: Ca | W33: 92805 | Y33: katie@anaheimwhitehouse.com | AL33: 54-230 | AM33: CC235 | AO33: 62245 | AU33: 887 S. Anaheim Blvd | AW33: Anaheim | AX33: Ca | AY33: 92805 | AZ33: 714-772-1381
A34: Ananda Fuara | B34: SUPPLY ONLY | C34: AH | E34: NO | H34: NO | K34: 44760 | M34: 43649 | N34: Golapendu | O34: 415-621-1994 | P34: 415-812-1327 | Q34: 0.08625 | R34: 0.0875 | S34: SF | T34: 1298 Market Street | U34: San Francisco | V34: Ca | W34: 94102 | AL34: 54230 | AM34: 13305 | AO34: 67240 | AU34: 1298 Market Street | AW34: San Francisco | AX34: Ca | AY34: 94102 | AZ34: 415-621-1994
A35: Anderson Valley Brewing | B35: SUPPLY ONLY | C35: AH | E35: NO | H35: NO | K35: 43675 | N35: Rebecca | O35: 707-895-2337 | Q35: 0.07875 | R35: 0.0762 | S35: Mendo | T35: 17700 Highway 253 | U35: Boonville | V35: Ca | W35: 95415 | X35: reception@avbc.com | Y35: rpaez@avbc.com | AA35: Vicky ( A/P) | AI35: 707-895-2353 | AL35: 54-230 | AU35: P.O. Box 505 | AV35: 17700 HIGHWAY 253 | AW35: Boonville | AX35: Ca | AY35: 95415 | AZ35: 707-895-2337
A36: Andi's Market | B36: NCC | C36: LG | D36: 570-2 | E36: NO | H36: NO | K36: 45979 | M36: 44897 | N36: Morris | O36: 415-648-4656 | P36: 559-960-2025 cell | Q36: 0.08625 | R36: 0.0875 | S36: SF | T36: 820 Cortland Avenue | U36: San Francisco | V36: Ca | W36: 94110 | X36: mlmanji@gmail.com | Y36: mlmanji@gmail.com | Z36: mlmanji@gmail.com | AL36: 54-230 | AM36: 15185 | AQ36: GoDex /roll | AU36: 820 Cortland Avenue | AW36: San Francisco | AX36: Ca | AY36: 94110 | AZ36: 415-648-4656
A37: Andy & Yu's | B37: SpotOn | C37: AH | E37: 7 X 24 | F37: SpotOn | H37: NO | K37: 45454 | M37: 45434 | N37: Nicole | O37: 925-750-8888 | Q37: 0.1025 | S37: Pleas | T37: 348 St.Mary Street | U37: Pleasanton | V37: Ca | W37: 94566 | AU37: 348 St. Mary Street | AW37: Pleasanton | AX37: Ca | AY37: 94566 | AZ37: 925-750-8888
A38: Andy's Local Market | B38: SUPPLY ONLY | C38: AH | E38: NO | H38: NO | K38: 45453 | N38: Paige/Robert | O38: 415-456-5730 | Q38: 0.0925 | S38: SR | T38: 75 Loch Lomond Drive | U38: San Rafael | V38: Ca | W38: 94901 | X38: bernie@andyslocalmarket.com | AL38: 54-230 | AN38: CC235 | AO38: 62245 | AP38: 18-333 | AU38: 75 Loch Lomond Drive | AW38: San Rafael | AX38: Ca | AY38: 94901 | AZ38: 415-456-5730
A39: Angela's Kitchen | B39: SUPPLY ONLY | C39: AH | E39: NO | H39: NO | K39: 44594 | N39: Saboor | O39: 510-263-8788 | P39: 510-333-4874 | Q39: 0.1075 | R39: 0.095 | S39: ALA | T39: 1640 Park Street | U39: Alameda | V39: Ca | W39: 94501 | X39: zboor58@gmail.com | Y39: zboor58@gmail.com | AA39: Lisa | AI39: 510-864-0803 | AL39: 54-230 | AM39: 18333 | AO39: 67240 | AU39: 1640 Park Street | AW39: Alameda | AX39: Ca | AY39: 94501 | AZ39: 510-522-5822
A40: Antigua Cocina | B40: ECR | C40: AH | D40: SAM4S ER260 | E40: NO | H40: NO | M40: 44400 | N40: Marvin | O40: 415-879-6670 | Q40: 0.0925 | S40: Novato | T40: 1559 S. Novato Blvd, Suite J | U40: Novato | V40: Ca | W40: 94945 | AU40: 1559 S. Novato Blvd | AW40: Novato | AX40: Ca | AY40: 94945 | AZ40: 415-879-6670
A41: Antonio's Quick Lunch | B41: SUPPLY ONLY | C41: AH | E41: NO | H41: NO | K41: 43742 | M41: 44573 | N41: Antonio | O41: 530-763-4009 | P41: 530-751-6902 | Q41: 0.0725 | R41: 0.075 | S41: SUTTER | T41: 716 Colusa Avenue | U41: Yuba City | V41: Ca | W41: 95991 | X41: aql761@hotmail.com | AA41: Mayra | AB41: 530-300-3551 cell | AL41: 54-230 | AM41: 13305 | AO41: 62245 | AU41: 716 Colusa Avenue | AW41: Yuba City | AX41: Ca | AY41: 95991 | AZ41: 530-751-6902
A42: Armando's Bar & Grill | B42: SPOTON | C42: JS | E42: 7 X 24 | F42: SpotOn | H42: DEPOT | I42: SPOTON | K42: 45897 | M42: 44916 | N42: Armando Alvarez | O42: 760-346-0744 | P42: 760-972-7118 | Q42: 0.0875 | R42: 0.08 | S42: Riverside | T42: 73260 El Paseo #1A | U42: Palm Desert | V42: Ca | W42: 92260 | X42: armandononi@hotmail.com | Y42: amandaalvarez89@gmail.com | Z42: jysrosales2@msn.com | AA42: Javier Rosales | AI42: 760-346-0741 | AL42: 54-230 | AM42: 13305 | AN42: 15185 | AO42: 62245 | AU42: 73260 El Paseo #1A | AW42: Palm Desert | AX42: Ca | AY42: 92260 | AZ42: 760-346-0744
A43: Arteaga's Food Center - Lodi | B43: SUPPLY ONLY | C43: AH | E43: NO | H43: NO | M43: 43551 | N43: Alonzo Lopez | O43: 209-339-0399 | P43: 510-376-9832 | Q43: 0.0825 | R43: 0.08 | S43: Lodi | T43: 200 E Oak Street | U43: Lodi | V43: Ca | W43: 95240 | X43: alonzo@arteagas.com | AA43: Claudia | AB43: 707-318-6841 | AI43: 408-885-0808 | AU43: 200 E Oak Street | AW43: Lodi | AX43: Ca | AY43: 95240 | AZ43: 209-339-0399
A44: Arteaga's Food Center - Newark | B44: SUPPLY ONLY | C44: AH | E44: NO | H44: NO | K44: 44769 | M44: 44250 | N44: Geraldo Lopez | O44: 510-791-1252 | P44: 510-364-8854 | Q44: 0.1075 | R44: 0.095 | S44: Newark | T44: 5524 Thornton Avenue | U44: Newark | V44: Ca | W44: 94560 | X44: glopez@arteagasfoodcenter.com | Y44: nelson@arteagas.com | AA44: Lorena= A/P | AC44: Jose | AI44: 408-899-6939 | AJ44: 510-744-0776 | AM44: 13305 | AO44: 62245 | AU44: 5524 Thornton Avenue | AW44: Newark | AX44: Ca | AY44: 94560 | AZ44: 510-791-1252
A45: Arya Steakhouse- Palo Alto | B45: SPOT ON | C45: NS | E45: 7 X 24 | F45: SpotOn | M45: 44782 | N45: Fera | O45: 650-304-3119 | Q45: 0.09125 | S45: SC | T45: 140 University Ave | U45: Palo Alto | V45: Ca | W45: 94301 | X45: fera@aryarestaurant.com | AL45: 54-230 | AU45: 140 University Ave | AW45: Palo Alto | AX45: Ca | AY45: 94301 | AZ45: 650-304-3119
A46: Asian Box - Palo Alto | B46: SPOT ON | C46: SO | E46: 7 X 24 | F46: SpotOn | K46: 44705 | N46: Charles Imerson | O46: 650-391-9305 | Q46: 0.09125 | S46: SC | T46: 855 El Camino Real | U46: Palo Alto | V46: Ca | W46: 94301 | X46: asianbox@info.com | Y46: asianbox@info.com | Z46: asianbox@info.com | AL46: 15741 | AU46: 855 El Camino Real | AW46: Palo Alto | AX46: Ca | AY46: 94301 | AZ46: 650-391-9305
A47: Atlas Café | B47: SUPPLY ONLY | C47: AH | E47: NO | H47: NO | K47: 43333 | M47: 43178 | N47: Bill Stone | O47: 415-648-1047 | P47: 415-999-6274 | Q47: 0.08625 | R47: 0.0875 | S47: SF | T47: 3049 20th Street | U47: San Francisco | V47: Ca | W47: 94110 | AL47: 54-230 | AM47: 13305 | AN47: 54170 | AO47: 62245 | AU47: =PROPER(AV47) -> 3049 20Th Street | AV47: 3049 20TH STREET | AW47: San Francisco | AX47: Ca | AY47: 94110 | AZ47: 415-648-1047
A48: Atwater Tavern | B48: SUPPLY ONLY | C48: AH | E48: NO | H48: NO | K48: 45932 | N48: John Caine | O48: 415-512-7153 | Q48: 0.08625 | R48: 0.0875 | S48: SF | T48: 295 Terry A Francois Blvd | U48: San Francisco | V48: Ca | W48: 94158 | X48: fanny@atwatertavern.com | Y48: joshua@mas.us.com | Z48: john@atwatertavern.com | AA48: EMAIL Debbie invoices!!!! | AJ48: Jameson AP | AL48: 54230 | AM48: 13305 | AN48: cc235 | AO48: 62245 | AU48: 289 Terry A Francois Blvd | AW48: San Francisco | AX48: Ca | AY48: 94158 | AZ48: 415-512-7153
A49: Augie's French | B49: SPOT ON | C49: AH | E49: NO | H49: NO | K49: 45881 | N49: Kim | O49: 707-531-4400 | Q49: 0.1 | S49: S.Rosa | T49: 535 4th Street | U49: Santa Rosa | V49: Ca | W49: 94501 | AL49: 54-230 | AN49: CC235 | AO49: 62245 | AU49: 535 4th Street | AW49: Santa Rosa | AX49: Ca | AY49: 94501
A50: Aurora - Sausalito | B50: SPOT ON | C50: AH | E50: 7 X 24 | F50: SpotOn | K50: 44727 | N50: Vanessa Romero | O50: 415-339-8930 | Q50: 0.0925 | S50: Saus | T50: 300 Valley St Ste 207 | U50: Sausalito | V50: Ca | W50: 94965 | X50: info@aurorasausalito.com | Y50: info@aurorasausalito.com | Z50: info@aurorasausalito.com | AU50: 300 Valley St Ste 207 | AW50: Sausalito | AX50: Ca | AY50: 94965 | AZ50: 415-339-8930
A51: Auto City | B51: SUPPLY ONLY | C51: AH | E51: NO | H51: NO | K51: 44572 | M51: 43844 | N51: Roberto | O51: 415-713-5409 | Q51: 0.08625 | S51: SF | T51: 501 South Van Ness Avenue | U51: San Francisco | V51: Ca | W51: 94110 | AL51: 63544 | AM51: 15157 | AO51: 61085 $6ea | AU51: 501 South Van Ness Avenue | AW51: San Francisco | AX51: Ca | AY51: 94110 | AZ51: 415-713-5409
A52: Avenue Liquor | B52: Sam4s | C52: AH | D52: 6600 | E52: NO | H52: NO | M52: 44995 | N52: Gurmeet | O52: 650-368-8864 | P52: 415-571-5609 | Q52: 0.09875 | S52: RWC | T52: 2147 Roosevelt Ave | U52: Redwood City | V52: Ca | W52: 94061 | AU52: 2147 Roosevelt Ave | AW52: Redwood City | AX52: Ca | AY52: 94061 | AZ52: 650-368-8864
A53: Baan Thai Restaurant | B53: SUPPLY ONLY | C53: AH | E53: NO | H53: NO | K53: 45189 | N53: Carlos | O53: 831-394-2996 | P53: 831-521-3365 | Q53: 0.0925 | S53: Monterey | T53: 1760 Fremont Blvd #F1 | U53: Seaside | V53: Ca | W53: 93955 | AL53: 54-230 | AM53: 13305 | AO53: 62245 | AU53: 1760 Fremont Blvd #F1 | AW53: Seaside | AX53: Ca | AY53: 93955 | AZ53: 831-521-3365
A54: Baan Thai- San Anselmo | B54: SUPPLY ONLY | C54: AH | E54: NO | H54: NO | K54: 45131 | N54: Jackie | O54: 415-457-9470 | Q54: 0.0925 | S54: S.Ansel | T54: 726 San Anselmo Ave | U54: San Anselmo | V54: Ca | W54: 94960 | AM54: 13305 | AO54: 62245 | AU54: 726 San Anselmo Ave | AW54: San Anselmo | AX54: Ca | AY54: 94960 | AZ54: 415-457-9470
A55: Bacco Ristorante Italiano | B55: SPOT ON | C55: RA | E55: 7 X 24 | F55: SpotOn | K55: 44790 | N55: Shari | O55: 415-370-2191 | Q55: 0.08625 | S55: SF | T55: 3913 24th Street | U55: San Francisco | V55: Ca | W55: 94114 | X55: sipdominici@yahoo.com | Y55: sipdominici@yahoo.com | Z55: sipdominici@yahoo.com | AL55: 54-230 | AM55: 13-305 | AO55: 62245 | AU55: 3913 24th Street | AW55: San Francisco | AX55: Ca | AY55: 94114 | AZ55: 415-370-2191
A56: Baker St Café | B56: SUPPLY ONLY | C56: AH | E56: NO | H56: NO | K56: 44348 | M56: 44348 | N56: Kevin | O56: 650-593-0103 | Q56: 0.09875 | S56: RWC | T56: 254 Redwood Shores Pkwy | U56: Redwood City | V56: Ca | W56: 94065 | AU56: 254 Redwood Shores Pkwy | AW56: Redwood City | AX56: Ca | AY56: 94065 | AZ56: 650-593-0103
A57: Baltic Spice House | B57: SUPPLY ONLY | C57: AH | E57: NO | H57: NO | K57: 44503 | M57: 44470 | N57: Harjinder Singh | O57: 916-465-5925 | Q57: 0.0975 | S57: Richmond | T57: 135 Park Pl | U57: Richmond | V57: Ca | W57: 94801 | X57: harjindersingh4414@yahoo.com | Y57: harjindersingh4414@yahoo.com | Z57: harjindersingh4414@yahoo.com | AU57: 135 Park Pl | AW57: Richmond | AX57: Ca | AY57: 94801 | AZ57: 916-465-5925
A58: Banzai Japanese Bar & Grill | B58: SUPPLY ONLY | C58: AH | E58: NO | H58: NO | K58: 44271 | N58: David Rasavong | Q58: 0.0835 | S58: FresCity | T58: 609 E Olive Ave Suite C | U58: Fresno | V58: Ca | W58: 94110 | Y58: Elev8tehospitality@gmail.con | AL58: 15185 | AM58: CC235 | AO58: 62245 | AU58: 609 E Olive Ave Suite C | AW58: Fresno | AX58: Ca | AY58: 94110
A59: Bar Bocce | B59: SUPPLY ONLY | C59: RF | E59: NO | H59: NO | K59: 44816 | M59: 44830 | N59: Gary Newman | O59: 415-331-0555 | Q59: 0.0925 | R59: 0.09 | S59: Saus | T59: 1250 Bridgeway Blvd | U59: Sausalito | V59: Ca | W59: 94965 | X59: gary@barbocce.com | Y59: gary@barbocce.com | Z59: info@barbocce.com | AA59: Lauren GM | AB59: 415-342-1668 | AK59: www.barbocce.com | AL59: 54-230 | AM59: 13305 | AO59: 62245 | AP59: 62235 | AT59: P. Schumaker | AU59: 1250 Bridgeway Blvd | AW59: Sausalito | AX59: Ca | AY59: 94965 | AZ59: 415-331-0555
A60: Bar Cava | B60: SUPPLY ONLY | C60: AH | E60: NO | H60: NO | K60: 44420 | N60: Hailey | O60: 925-957-6030 | Q60: 0.0975 | S60: Martinez | T60: 718 Main Street | U60: Martinez | V60: Ca | W60: 94553 | AU60: 718 Main Street | AW60: Martinez | AX60: Ca | AY60: 94553 | AZ60: 925-957-6030
A61: Barbacco Entrattoria | B61: SPOT ON | C61: DO | E61: 7 X 24 | F61: SpotOn | N61: Umberto Gibin | O61: 415-955-1919 | Q61: 0.08625 | S61: SF | T61: 220 California St | U61: San Francisco | V61: Ca | W61: 94111 | X61: umberto+1@perbaccosf.com | Y61: umberto+1@perbaccosf.com | Z61: umberto+1@perbaccosf.com | AU61: 220 California St | AW61: San Francisco | AX61: Ca | AY61: 94111 | AZ61: 415-955-1919
A62: Barrel Head Brewhouse | B62: SUPPLY ONLY | C62: AH | E62: NO | H62: NO | K62: 45320 | N62: Natasha Gatto | O62: 415-416-6989 | Q62: 0.08625 | R62: 0.0875 | S62: SF | T62: 1785 Fulton Street | U62: San Francisco | V62: Ca | W62: 94117 | X62: natasha@barrelheadsf.com | AL62: 54-230 | AM62: 13305 | AN62: CC235 | AO62: 62245 | AU62: 1785 Fulton Street | AW62: San Francisco | AX62: Ca | AY62: 94117 | AZ62: 415-416-6989
A63: Barrel House Tavern | B63: SPOT ON | C63: DO | E63: 7 X 24 | F63: SpotOn | K63: 45982 | M63: 45593 | N63: Christian Henry | O63: 415-729-9593 | P63: 415-260-1293 | Q63: 0.0925 | R63: 0.09 | S63: Saus | T63: 660 Bridgeway | U63: Sausalito | V63: Ca | W63: 94965 | X63: jaredpfeldman@gmail.com | Y63: barrelhouse2000@gmail.com | Z63: chenry39@comcast.net | AL63: 54-230 | AM63: 13305 | AO63: 62245 | AU63: 660 Bridgeway | AW63: Sausalito | AX63: Ca | AY63: 94965 | AZ63: 415-729-9593
A64: Batika India Cuisine | B64: SUPPLY ONLY | C64: AH | E64: 7 x 24 | F64: SpotOn | K64: 45629 | N64: Arun | O64: 415-897-5757 | Q64: 0.085 | S64: Nov | T64: 868 Grant Street | U64: Novato | V64: Ca | W64: 94945 | AL64: 54-230 | AN64: CC235 | AU64: 868 Grant Avenue | AW64: Novato | AX64: Ca | AY64: 94945 | AZ64: 415-897-5757
A65: Bay Area Market & Liquor | B65: CASIO | C65: LG | D65: Casio TE7000 | E65: NO | H65: NO | K65: 45558 | M65: 45688 | N65: Yassir | O65: 510-658-4539 | Q65: 0.1025 | R65: 0.095 | S65: ALA | T65: 3148 San Pablo Avenue | U65: Oakland | V65: Ca | W65: 94608 | Y65: y2ma@yahoo.com | AA65: Mageed Alwasim | AB65: 510-599-3129 | AL65: 15157 | AU65: 3148 San Pablo Avenue | AW65: Oakland | AX65: Ca | AY65: 94608 | AZ65: 510-658-4539
A66: Bellam Produce | B66: ECR | C66: AH | D66: Er-945 | E66: NO | H66: NO | K66: 45932 | M66: 45499 | N66: Thomas | O66: 415-256-8086 | P66: 415-902-8812 | Q66: 0.0925 | R66: 0.0925 | S66: SR | T66: 151 Bellam Blvd | U66: San Rafael | V66: Ca | W66: 94901 | AA66: Tom | AB66: 415-902-8812 | AL66: 15157 | AM66: 44150 | AN66: 15741 | AO66: 67655 | AU66: =PROPER(AV66) -> 151 Bellam Blvd | AV66: 151 BELLAM BLVD | AW66: San Rafael | AX66: Ca | AY66: 94901 | AZ66: 415-256-9837
A67: Bellam Self Storage | B67: SUPPLY ONLY | C67: AH | E67: NO | H67: NO | K67: 45663 | N67: Andree | O67: 415-454-1983 | Q67: 0.0925 | R67: 0.0925 | S67: SR | T67: 24 Bellam Blvd | U67: San Rafael | V67: Ca | W67: 94901 | AL67: 13305 | AN67: CC235 | AU67: PO Box 10788 | AW67: San Rafael | AX67: Ca | AY67: 94912 | AZ67: 415-454-1983
A68: Ben Franklin | B68: SUPPLY ONLY | C68: AH | E68: NO | H68: NO | K68: 45042 | N68: Jennifer | O68: 530-273-1348 | Q68: 0.08875 | R68: 0.0762 | S68: Grass Val | T68: 598 Sutton Way | U68: Grass Valley | V68: Ca | W68: 95945 | AA68: Jeannie DeGruccio | AI68: 530-272-6452 | AL68: 54-230 | AU68: 598 Sutton Way | AW68: Grass Valley | AX68: Ca | AY68: 95945 | AZ68: 530-273-1348
A69: Beretta | B69: SUPPLY ONLY | C69: AH | E69: NO | H69: NO | K69: 44215 | M69: 44551 | N69: Marko | O69: 415-695-1199 | Q69: 0.08625 | R69: 0.0875 | S69: SF | T69: 1199 Valencia Street | U69: San Francisco | V69: Ca | W69: 94110 | X69: rodrigo@backofthehouseinc.com | Y69: info@berettasf.com | AL69: 54-230 | AM69: 13305 | AN69: CC235 | AO69: 62245 | AU69: 1199 Valencia Street | AW69: San Francisco | AX69: Ca | AY69: 94110 | AZ69: 415-881-7020
A70: Berkeley Bagel | B70: ECR | C70: AH | E70: NO | H70: NO | K70: 43468 | M70: 44594 | N70: Sam Chea | O70: 510-524-3104 | P70: 408-823-8999 cell | Q70: 0.1025 | R70: 0.095 | S70: ALA | T70: 1281 Gilman St | U70: Berkeley | V70: Ca | W70: 94706 | AL70: 15741 | AU70: 1281 Gilman St | AW70: Berkeley | AX70: Ca | AY70: 94706 | AZ70: 510-524-3104
A71: Beso | B71: SpotOn | C71: RA | E71: 7 x 24 | F71: SpotOn | H71: NO | K71: 44817 | M71: 44039 | N71: Michelle | O71: 415-883-6700 | P71: 615-419-4003 | Q71: 0.0925 | R71: 0.09 | S71: Novato | T71: 502 S. Palm Drive | U71: Novato | V71: Ca | W71: 94949 | X71: beso@fe.fake | Y71: beso@fe.fake | Z71: beso@fe.fake | AL71: 54-230 | AO71: 62245 | AT71: Michelle | AU71: 502 S. Palm Drive | AW71: Novato | AX71: Ca | AY71: 94949 | AZ71: 415-883-6700
A72: Beyond the Glory | B72: SUPPLY ONLY | C72: AH | E72: NO | H72: NO | K72: 44433 | N72: Colby- MGR | O72: 707-971-8366 | P72: 707-338-3211 | Q72: 0.1025 | S72: Petaluma | T72: 1371 N McDowell Blvd Suite 130 | U72: Petaluma | V72: Ca | W72: 94954 | AA72: Jeffrey Inglin- owner | AB72: 623-518-0818 | AU72: 1371 N McDowell Blvd Suite 130 | AW72: Petaluma | AX72: Ca | AY72: 94954 | AZ72: 707-971-8366
A73: Bird & The Bottle | B73: SUPPLY ONLY | C73: AH | E73: NO | H73: NO | K73: 45418 | N73: Sam | O73: 707-568-4000 | Q73: 0.1 | S73: S.Rosa | T73: 1055 4th St | U73: Santa Rosa | V73: Ca | W73: 95404 | X73: info@birdandthebottle.com | Y73: info@birdandthebottle.com | Z73: info@birdandthebottle.com | AL73: 54-230 | AM73: 13305 | AO73: 62245 | AU73: 1055 4th St | AW73: Santa Rosa | AX73: Ca | AY73: 95404 | AZ73: 707-568-4000
A74: Bistro 45 | B74: SUPPLY ONLY | C74: AH | D74: SNBC | E74: NO | H74: NO | K74: 45951 | N74: Robert Simon | O74: 626-795-2478 | P74: 626-644-9387 cell | Q74: 0.105 | R74: 0.09 | S74: Pasa | T74: 45 South Mentor Avenue | U74: Pasadena | V74: Ca | W74: 91106 | X74: edward@welldonebooks.com | AL74: 54-230 | AM74: 13305 | AN74: CC235 | AO74: 62245 | AU74: 45 South Mentor Avenue | AW74: Pasadena | AX74: Ca | AY74: 91106 | AZ74: 626-795-2478
A75: Black & White Market | B75: ECR | C75: LG | D75: Casio Te-2200 | E75: NO | H75: NO | M75: 44398 | N75: Judy/Hung | O75: 510-261-2681 | Q75: 0.1025 | S75: ALA | T75: 2681 Fruitvale Blvd | U75: Oakland | V75: Ca | W75: 94601 | AU75: 2681 Fruitvale Blvd | AW75: Oakland | AX75: Ca | AY75: 94601 | AZ75: 510-261-2681
A76: Blue & Gold Fleet | B76: SUPPLY ONLY | C76: AH | E76: NO | H76: NO | K76: 45076 | M76: 43042 | N76: Stacy | O76: 415-705-5458 | P76: 415-705-5532 (after 3) | Q76: 0.08625 | R76: 0.0875 | S76: SF | T76: Pier 41 Marina Terminal, 2nd Floor | U76: San Francisco | V76: Ca | W76: 94133 | AA76: ARLENE | AB76: 415-705-5458 | AC76: Kent | AD76: 415-407-2000 | AI76: 415-705-5429 | AK76: www.blueandgoldfleet.com | AL76: 54-230 | AM76: 12100 | AU76: Pier 41 Marina Terminal, 2nd Floor | AV76: PIER 41 MARINA | AW76: San Francisco | AX76: Ca | AY76: 94133 | AZ76: 415-705-8265
A77: Blue Barn - Novato | B77: Spoton | C77: AH | E77: 7 X 24 | F77: SpotOn | K77: 45735 | N77: Neusa | O77: 415-895-6771 | Q77: 0.0925 | S77: Novato | T77: 819 Grant Avenue | U77: Novato | V77: Ca | W77: 94945 | AL77: 54-230 | AM77: 13-305 | AO77: 62245 | AU77: 819 Grant Avenue | AW77: Novato | AX77: Ca | AY77: 94945 | AZ77: 415-895-6771
A78: Blue Barn- Cole | B78: Spot On | C78: AH | E78: 7 x 24 | F78: SpotOn | H78: NO | K78: 45727 | N78: Juan | Q78: 0.08625 | S78: SF | T78: 901 Cole Street | U78: San Francisco | V78: Ca | W78: 94117 | AL78: 54-230 | AN78: CC235 | AO78: 62245 | AU78: 901 Cole Street | AW78: San Francisco | AX78: Ca | AY78: 94117
A79: Blue Barn- Corte Madera | B79: SPOT ON | C79: AH | E79: 7 X 24 | F79: SpotOn | H79: Spot On | K79: 45748 | N79: Liz | O79: 415-927-1104 | Q79: 0.09 | S79: CM | T79: 335 Corte Madera Town Center | U79: Corte Madera | V79: Ca | W79: 94925 | AL79: 54-230 | AM79: CC235 | AU79: 335 Corte Madera Town Center | AW79: Corte Madera | AX79: Ca | AY79: 94925 | AZ79: 415-927-1104
A80: Blue Barn- Polk | B80: Spot On | C80: AH | E80: 7 X 24 | F80: SpotOn | H80: Spot On | K80: 45723 | N80: Caroline | O80: 415-655-9438 | Q80: 0.08625 | S80: SF | T80: 2237 Polk St | U80: San Francisco | V80: Ca | W80: 94109 | AL80: 54-230 | AM80: cc235 | AO80: 62245 | AU80: 2237 Polk Street | AW80: San Francisco | AX80: Ca | AY80: 94109 | AZ80: 415-655-9438
A81: Blue Barn- Steiner | B81: Spot On | C81: AH | E81: 7 X 24 | F81: SpotOn | H81: Spot On | K81: 45723 | N81: Caitlyn | O81: 415-896-4866 | Q81: 0.08625 | S81: SF | T81: 3344 Steiner St | U81: San Francisco | V81: Ca | W81: 94123 | AL81: 54-230 | AM81: CC235 | AO81: 62245 | AU81: 3344 Steiner St | AW81: San Francisco | AX81: Ca | AY81: 94123 | AZ81: 415-896-4866
A82: Blue Heron | B82: NCC | C82: DK | E82: NO | H82: NO | K82: 45527 | M82: 43542 | N82: Tom | O82: 707-865-2261 | P82: 530-220-2475 | Q82: 0.0925 | R82: 0.0825 | S82: SON | T82: 25275 Steelhead Blvd | U82: Jenner | V82: Ca | W82: 95450 | X82: blueheronlive@gmail.com | AL82: 54-230 | AM82: CC235 | AN82: 15185 | AO82: 62245 | AU82: PO Box 32 | AV82: 25300 STEELHEAD BLVD | AW82: Duncan Mills | AX82: Ca | AY82: 95430 | AZ82: 707-865-9135
A83: Blue Whale SF | B83: SPOTON | C83: AH | E83: 7 X 24 | F83: SpotOn | H83: NO | K83: 45211 | N83: David | O83: 415-812-7984 | Q83: 0.08625 | S83: SF | T83: 2033 Union Street | U83: San Francisco | V83: Ca | W83: 94123 | AO83: 62245 | AU83: 2033 UnionStreet | AW83: San Francisco | AX83: Ca | AY83: 94123
A84: Boboquivari's | B84: SUPPLY ONLY | C84: AH | E84: NO | H84: NO | K84: 45646 | N84: Thomas | O84: 415-441-8880 | Q84: 0.08625 | S84: SF | T84: 1450B Lombard St | U84: San Francisco | V84: Ca | W84: 94123 | X84: tbunker@boboquivaris.com | AL84: 54-230 | AM84: 13305 | AO84: 62245 | AU84: 1450 Lombard St | AW84: San Francisco | AX84: Ca | AY84: 94123 | AZ84: 415-441-8880
A85: Boca Pizza - Corte Madera | B85: SUPPLY ONLY | C85: AH | E85: NO | H85: NO | K85: 45454 | N85: George | O85: 415-924-3021 | P85: 510-734-9054 | Q85: 0.09 | R85: 0.09 | S85: CorteM | T85: 1544 Redwood Highway | U85: Corte Madera | V85: Ca | W85: 94925 | X85: omar@bocapizzeria.com | Y85: <== A/P | AA85: Manny | AI85: 415-924-3024 | AK85: www.bocapizzeria.com/contact_cm.html | AL85: 54-230 | AM85: 13305 | AN85: CC235 | AO85: 62245 | AU85: 1544 Redwood Highway | AW85: Corte Madera | AX85: Ca | AY85: 94925 | AZ85: 415-924-3021
A86: Boca Pizza - Novato | B86: SUPPLY ONLY | C86: AH | E86: NO | H86: NO | K86: 45391 | N86: Mario | O86: 415-883-2302 | Q86: 0.0925 | R86: 0.09 | S86: Novato | T86: 454 Ignacio Blvd | U86: Novato | V86: Ca | W86: 94949 | X86: omar@bocapizzeria.com | Y86: <== A/P | AA86: Greg | AC86: Ed | AE86: Sebastian | AK86: www.bocapizzeria.com | AL86: 54-230 | AM86: 13305 | AN86: CC235 | AO86: 62245 | AU86: 454 Ignacio Blvd | AW86: Novato | AX86: Ca | AY86: 94949 | AZ86: 415-883-2302
A87: Boca Tavern | B87: SUPPLY ONLY | C87: AH | E87: NO | H87: NO | K87: 43369 | N87: Brian Penly | O87: 415-883-0901 | Q87: 0.0925 | R87: 0.09 | S87: Novato | T87: 340 Ignacio Blvd | U87: Novato | V87: Ca | W87: 94949 | X87: brian@bocatavern.com | AA87: Felipe | AI87: 415-883-2802 | AL87: 54-230 | AM87: 13305 | AN87: CC235 | AO87: 62245 | AU87: 340 Ignacio Blvd | AW87: Novato | AX87: Ca | AY87: 94949 | AZ87: 415-883-0901
A88: Bolinas Peoples Store | B88: NCC | C88: LG | E88: 7 X 24 | F88: SpotOn | H88: NO | K88: 45999 | M88: 44519 | N88: Claire | O88: 415-868-1433 | Q88: 0.0825 | S88: Marin | T88: 14 Wharf Rd | U88: Bolinas | V88: Ca | W88: 94924 | AL88: 54-230 | AU88: 14 Wharf Rd | AW88: Bolinas | AX88: Ca | AY88: 94924 | AZ88: 415-868-1433
A89: Bonita Taqueria - 16th St | B89: SPOT ON | C89: NM | E89: 7 X 24 | F89: SpotOn | N89: Issa Sweidan | O89: 415-552-2125 | P89: 415-487-0551 | Q89: 0.08625 | S89: SF | T89: 3600 16th St | U89: San Francisco | V89: Ca | W89: 94114 | X89: jj@squatandgobble.com | Y89: jj@squatandgobble.com | Z89: jj@squatandgobble.com | AU89: 3600 16th St | AW89: San Francisco | AX89: Ca | AY89: 94114 | AZ89: 415-552-2125
A90: Bonita Taqueria - Chestnut | B90: SPOT ON | C90: NM | E90: 7 X 24 | F90: SpotOn | N90: Jawad Sweidan | O90: 415-801-5599 | P90: 415-702-6272 | Q90: 0.0863 | S90: SF | T90: 2257 Chestnut St | U90: San Francisco | V90: Ca | W90: 94123 | X90: jj+1@squatandgobble.com | Y90: jj+1@squatandgobble.com | Z90: jj+1@squatandgobble.com | AU90: 2257 Chestnut St | AW90: San Francisco | AX90: Ca | AY90: 91423 | AZ90: 415-801-5599
A91: Bottleneck Liquor | B91: ECR | C91: LG | D91: CASIO TE7000 | E91: NO | H91: NO | M91: 44223 | N91: Angrej | O91: 510-562-3612 | Q91: 0.1025 | S91: ALA | T91: 3151 98th Ave | U91: Oakland | V91: Ca | W91: 94605 | AU91: 3151 98th Ave | AW91: Oakland | AX91: Ca | AY91: 94605 | AZ91: 510-562-3612
A92: Bravas de Tapas | B92: SUPPLY ONLY | C92: SG | E92: NO | H92: NO | K92: 46000 | N92: Braxton/Nora | O92: 707-433-7700 | P92: 916-705-4766 | Q92: 0.0975 | S92: Heald | T92: 420 Center St | U92: Healdsburg | V92: Ca | W92: 95448 | X92: info@barbravas.com | Y92: info@barbravas.com | Z92: info@barbravas.com | AL92: 54-230 | AM92: 13305 | AN92: 62245 | AU92: 420 Center St | AW92: Healdsburg | AX92: Ca | AY92: 95448 | AZ92: 707-433-7700
A93: Bret Harte Market | B93: ECR | C93: AH | D93: SAM 520 | E93: NO | H93: NO | K93: 45503 | M93: 44743 | N93: Monti | O93: 415-456-0163 | P93: 415-240-1759 | Q93: 0.0925 | R93: 0.0925 | S93: SR | T93: 93 Woodland Avenue | U93: San Rafael | V93: Ca | W93: 94901 | X93: JASWINDERSINGH101@YAHOO.COM | AA93: Jesse | AC93: Aman | AL93: 54-230 | AN93: 15741 | AQ93: GL2003 | AU93: =PROPER(AV93) -> 93 Woodland Avenue | AV93: 93 WOODLAND AVENUE | AW93: San Rafael | AX93: Ca | AY93: 94901 | AZ93: 415-456-0163
A94: Britannia Arms - Almaden | B94: SUPPLY ONLY | C94: AH | E94: NO | H94: NO | K94: 44662 | N94: Michael | O94: 408-266-0550 | Q94: 0.09375 | R94: 0.09 | S94: SanJose | T94: 5027 Almaden Expressway | U94: San Jose | V94: Ca | W94: 95118 | AA94: Debbie | AL94: 54-230 | AM94: 13305 | AO94: 62245 | AU94: 5027 Almaden Expressway | AW94: San Jose | AX94: Ca | AY94: 95118 | AZ94: 408-266-0550
A95: Britannia Arms - Downtown | B95: SUPPLY ONLY | C95: AH | E95: NO | H95: NO | K95: 43840 | M95: 43587 | N95: Sonny Walters | O95: 408-278-1400 | P95: 650-676-7788 | Q95: 0.09375 | R95: 0.09 | S95: SanJose | T95: 173 W. Santa Clara Street | U95: San Jose | V95: Ca | W95: 95113 | X95: downtownbritarms@yahoo.com | AA95: Terry | AB95: 619-370-5554 | AC95: Bob / Antonio | AD95: 408-723-1337 | AE95: Dan | AF95: 408-981-2296% | AG95: Margaret | AI95: 408-278-1477 | AL95: 54-230 | AM95: 13305 | AN95: CC235 | AO95: 62245 | AP95: 62235 | AU95: =PROPER(AV95) -> 173 W. Santa Clara Street | AV95: 173 W. SANTA CLARA STREET | AW95: San Jose | AX95: Ca | AY95: 95113 | AZ95: 408-278-1400
A96: Buckeye Roadhouse | B96: SUPPLY ONLY | C96: RF | E96: NO | H96: NO | K96: 45966 | N96: Peter Schumacher | O96: 415-331-2600 | P96: 415-990-2013 | Q96: 0.0925 | R96: 0.085 | S96: Marin | T96: 15 Shoreline Highway | U96: Mill Valley | V96: Ca | W96: 94941 | X96: peterschumacher2@gmail.com | Y96: buckeyeroadhouse@comcast.net | AI96: 415-331-6067 | AL96: 54-230 | AM96: 13305 | AN96: CC235 | AO96: 62245 | AQ96: 15741 | AU96: 15 Shoreline Highway | AW96: Mill Valley | AX96: Ca | AY96: 94941 | AZ96: 415-331-2600
A97: Buffalo Billiards Pool Hall | B97: SPOT ON | C97: MB | E97: 7 X 24 | F97: SpotOn | K97: 45607 | N97: Mike Bombace | O97: 707-585-8992 | Q97: 0.1025 | S97: Petaluma | T97: 246 Petaluma Blvd N | U97: Petaluma | V97: Ca | W97: 94952 | AL97: 54-230 | AM97: 13305 | AO97: 62245 | AU97: 246 Petaluma Blvd N | AW97: Petaluma | AX97: Ca | AY97: 94952 | AZ97: 707-585-8992
A98: Bull Valley Roadhouse | B98: SUPPLY ONLY | C98: AH | E98: NO | H98: NO | K98: 45923 | N98: Paolo Gomez | O98: 510-787-1135 | Q98: 0.0875 | S98: CC | T98: 14 Canyon Lake Drive | U98: Port Costa | V98: Ca | W98: 94569 | X98: eric@bullvalleyroadhouse.com | Y98: accounting@bullvalleyroadhouse.com | Z98: eric@bullvalleyroadhouse.com | AL98: 54-230 | AM98: 13305 | AO98: 62245 | AU98: 14 Canyon Lake Dr.PO Box 106 | AW98: Port Costa | AX98: Ca | AY98: 94569 | AZ98: 510-787-1135
A99: Bungalow 44 | B99: SUPPLY ONLY | C99: RF | E99: NO | H99: NO | K99: 45838 | N99: Peter Schumacher | O99: 415-381-2500 | P99: 415-990-2013 | Q99: 0.0925 | R99: 0.085 | S99: Marin | T99: 44 E. Blithedale Road | U99: Mill Valley | V99: Ca | W99: 94941 | X99: peterschumacher2@gmail.com | Y99: tiffany@realrestaurants.com | Z99: tiffany@realrestaurants.com | AA99: Leslie Morgan=mgr | AB99: 415-342-6101 | AI99: 415-381-1476 | AL99: 54-230 | AM99: 13305 | AN99: CC235 | AO99: 62245 | AU99: 44 E. Blithedale Road | AW99: Mill Valley | AX99: Ca | AY99: 94941 | AZ99: 415-381-2500
A100: Butler Amusements | B100: ECR | C100: AH | D100: Sam 260 | E100: NO | H100: NO | K100: 44729 | M100: 44729 | N100: Dean | Q100: 0.1 | S100: S.Rosa | T100: 1049 Ca 33 | U100: Santa Rosa | V100: Ca | W100: 95322 | AL100: 15157
...

Sheet TAX RATES 2025
A1: Effective Sales and Use Tax Rates | E1: 45748
A3: Location | B3: Rate | C3: County | D3: Type | E3: Notes
A5: Adelanto | B5: 0.0775 | C5: San Bernardino | D5: City
A6: Agoura Hills | B6: 0.095 | C6: Los Angeles | D6: City
A7: Alameda | B7: 0.1075 | C7: Alameda | D7: City
A8: Alameda County | B8: 0.1025 | C8: Alameda | D8: County
A9: Albany | B9: 0.1075 | C9: Alameda | D9: City
A10: Alhambra | B10: 0.105 | C10: Los Angeles | D10: City
A11: Aliso Viejo | B11: 0.0775 | C11: Orange | D11: City
A12: Alpine County | B12: 0.0725 | C12: Alpine | D12: County
A13: Alturas | B13: 0.0725 | C13: Modoc | D13: City
A14: Amador City | B14: 0.0775 | C14: Amador | D14: City
A15: Amador County | B15: 0.0775 | C15: Amador | D15: County
A16: American Canyon | B16: 0.0775 | C16: Napa | D16: City
... A120: Del Mar | B120: 0.0875 | C120: San Diego | D120: City
A121: Del Norte County | B121: 0.0725 | C121: Del Norte | D121: County | E121: This county tax rate applies to areas that are within the boundaries of any incorporated city within the county of Del Norte
A122: Del Norte County Unincorporated Area | B122: 0.0825 | C122: Del Norte | D122: County | E122: This county tax rate applies to areas that are not within the boundaries of any incorporated city within the county of Del Norte
A123: Del Rey Oaks | B123: 0.0925 | C123: Monterey | D123: City
A124: Delano | B124: 0.0825 | C124: Kern | D124: City
A125: Desert Hot Springs | B125: 0.0875 | C125: Riverside | D125: City
A126: Diamond Bar | B126: 0.095 | C126: Los Angeles | D126: City
A127: Dinuba | B127: 0.085 | C127: Tulare | D127: City
A128: Dixon | B128: 0.08375 | C128: Solano | D128: City
A129: Dorris | B129: 0.0725 | C129: Siskiyou | D129: City
A130: Dos Palos | B130: 0.0775 | C130: Merced | D130: City
A131: Downey | B131: 0.105 | C131: Los Angeles | D131: City
A132: Duarte | B132: 0.105 | C132: Los Angeles | D132: City
A133: Dublin | B133: 0.1025 | C133: Alameda | D133: City
A134: Dunsmuir | B134: 0.0775 | C134: Siskiyou | D134: City
... A218: Kerman | B218: 0.08975 | C218: Fresno | D218: City
A219: Kern County | B219: 0.0725 | C219: Kern | D219: County | E219: This county tax rate applies to areas that are within the boundaries of any incorporated city within the county of Kern
A220: Kern County Unincorporated Area | B220: 0.0825 | C220: Kern | D220: County | E220: This county tax rate applies to areas that are not within the boundaries of any incorporated city within the county of Kern
A221: King City | B221: 0.0875 | C221: Monterey | D221: City
A222: Kings County | B222: 0.0725 | C222: Kings | D222: County
A223: Kingsburg | B223: 0.08975 | C223: Fresno | D223: City
A224: La Canada Flintridge | B224: 0.105 | C224: Los Angeles | D224: City
A225: La Habra | B225: 0.0875 | C225: Orange | D225: City
A226: La Habra Heights | B226: 0.095 | C226: Los Angeles | D226: City
A227: La Mesa | B227: 0.085 | C227: San Diego | D227: City
A228: La Mirada | B228: 0.095 | C228: Los Angeles | D228: City
A229: La Palma | B229: 0.0875 | C229: Orange | D229: City
A230: La Puente | B230: 0.1025 | C230: Los Angeles | D230: City
A231: La Quinta | B231: 0.0875 | C231: Riverside | D231: City
A232: La Verne | B232: 0.105 | C232: Los Angeles | D232: City
... A440: Santa Cruz | B440: 0.0925 | C440: Santa Cruz | D440: City
A441: Santa Cruz County | B441: 0.085 | C441: Santa Cruz | D441: County | E441: This county tax rate applies to areas that are within the boundaries of any incorporated city within the county of Santa Cruz
A442: Santa Cruz County Unincorporated Area | B442: 0.09 | C442: Santa Cruz | D442: County | E442: This county tax rate applies to areas that are not within the boundaries of any incorporated city within the county of Santa Cruz
A443: Santa Fe Springs | B443: 0.1075 | C443: Los Angeles | D443: City
A444: Santa Maria | B444: 0.0875 | C444: Santa Barbara | D444: City
A445: Santa Monica | B445: 0.1075 | C445: Los Angeles | D445: City
A446: Santa Paula | B446: 0.0925 | C446: Ventura | D446: City
A447: Santa Rosa | B447: 0.1 | C447: Sonoma | D447: City
A448: Santee | B448: 0.0775 | C448: San Diego | D448: City
A449: Saratoga | B449: 0.09125 | C449: Santa Clara | D449: City
A450: Sausalito | B450: 0.0925 | C450: Marin | D450: City
A451: Scotts Valley | B451: 0.0975 | C451: Santa Cruz | D451: City
A452: Seal Beach | B452: 0.0925 | C452: Orange | D452: City
A453: Seaside | B453: 0.0925 | C453: Monterey | D453: City
A454: Sebastopol | B454: 0.1025 | C454: Sonoma | D454: City
... A544: Yuba City | B544: 0.0725 | C544: Sutter | D544: City
A545: Yuba County | B545: 0.0725 | C545: Yuba | D545: County | E545: This county tax rate applies to areas that are within the boundaries of any incorporated city within the county of Yuba.
A546: Yuba County Unincorporated Area | B546: 0.0825 | C546: Yuba | D546: County | E546: This county tax rate applies to areas that are not within the boundaries of any incorporated city within the county of Yuba
A547: Yucaipa | B547: 0.0875 | C547: San Bernardino | D547: City
A548: Yucca Valley | B548: 0.0875 | C548: San Bernardino | D548: City

Sheet Sell Items
C1: PPOS product list
C5: Item# | D5: Description | J5: Price | K5: Ext
B7: PAPER
B8: 1 | C8: # 54-230 | D8: Epson Thermal | F8: 3 1/8 x 230' | H8: 0668 | I8: 50 rolls | J8: 99 | K8: =B8*J8 -> 99
B9: 1 | C9: # 13-305 | D9: Epson Impact | F9: 3" one ply x 165 | I9: 50 rolls | J9: 59 | K9: =B9*J9 -> 59
B10: 1 | C10: # CC-235 | D10: 3" TWO ply | F10: Epson TMU-220 | H10: 0047 | I10: 50 rolls | J10: 76 | K10: =B10*J10 -> 76
B11: 1 | C11: # 15-741 | D11: CC Machine | F11: 2.25" x 74 feet | H11: 5061 | I11: 50 rolls | J11: 39 | K11: =B11*J11 -> 39
B13: 1 | C13: # 11-094 | D13: one ply paper | F13: 3" one ply x 194 | I13: 50 rolls | J13: 59 | K13: =B13*J13 -> 59
B14: 1 | C14: # 12-100 | D14: one ply paper | F14: 2 1/4" x 150 feet | H14: 0510 | I14: 100 rolls | J14: 84 | K14: =B14*J14 -> 84
B15: 1 | C15: # 13-305C | D15: one ply paper | F15: 3" one ply canary | H15: 2015 | I15: 50 rolls | J15: 77 | K15: =B15*J15 -> 77
B16: 1 | C16: # 13-305G | D16: one ply paper | F16: 3" one ply green | H16: 2016 | I16: 50 rolls | J16: 72 | K16: =B16*J16 -> 72
B17: 1 | C17: # 15-044 | D17: thermal paper | F17: 44mm x 230 feet | I17: 50 rolls | J17: 76 | K17: =B17*J17 -> 76
B18: 1 | C18: # 15-157 | D18: 2 1/4 x 230'thermal | F18: Cash Reg- Thermal | H18: 2983 | I18: 50 rolls | J18: 82 | K18: =B18*J18 -> 82
B19: 1 | C19: # 15-160 | D19: 2 1/4 x 60' thermal | F19: Verifone Thermal | I19: 50 rolls | J19: 39 | K19: =B19*J19 -> 39
B20: 1 | C20: # 15-185 | D20: 2 1/4 x 85' thermal | F20: Verifone Thermal | H20: 0549 | I20: 50 rolls | J20: 39 | K20: =B20*J20 -> 39
B21: 1 | C21: # 15-040 | D21: Poynt CC station | F21: 2.25" x 16 feet | H21: 5040 | I21: 50 rolls | J21: 29 | K21: =B21*J21 -> 29
B22: 1 | C22: # 15-303 | D22: thermal paper | F22: 2.25" x 42 feet | H22: 2981 | I22: 48 rolls | J22: 39 | K22: =B22*J22 -> 39
B23: 1 | C23: # 18-333 | D23: three ply paper | F23: 3" w/c/p | I23: 50 rolls | J23: 89 | K23: =B23*J23 -> 89
B24: 1 | C24: # 46-015 | D24: thermal paper | F24: 3" x 230 feet | I24: 50 rolls | J24: 103 | K24: =B24*J24 -> 103
B25: 1 | C25: # 46-175 | D25: thermal paper | F25: 3 1/8 Heavy | I25: 50 rolls | J25: 124 | K25: =B25*J25 -> 124
B26: 1 | C26: # 54-170 | D26: thermal paper | F26: 3 1/8" x 110 feet | I26: 50 rolls | J26: 62 | K26: =B26*J26 -> 62
B27: 1 | C27: # 54-273 | D27: thermal paper | F27: 3 1/8 x 273' | H27: 0566 | I27: 50 rolls | J27: 116 | K27: =B27*J27 -> 116
B28: 1 | C28: # 64-437 | D28: 44mm one ply paper | F28: 44mm x 150 ft | I28: 100 rolls | J28: 73 | K28: =B28*J28 -> 73
B29: 1 | C29: #15-350 | D29: 2 1/4" x 50' thermal | F29: 2.25" x 50 ft | H29: 8056 | I29: 50 rolls | J29: 22.95 | K29: =B29*J29 -> 22.95
B30: 1 | C30: # 15-999 | D30: POS paper rolls | F30: Other | J30: 59 | K30: =B30*J30 -> 59
B32: INK
B33: 1 | C33: # 62245 | D33: black/red ribbons | F33: EPSON TM-220 series | I33: Per Dozen | J33: 42 | K33: =B33*J33 -> 42
B34: 1 | C34: # 67240 | D34: black/red ribbons | F34: STAR SP700 series | I34: Per Dozen | J34: 52 | K34: =B34*J34 -> 52
B36: 1 | C36: # ERC-38 | D36: Epson black/red | F36: Epson TM-U2220 | I36: Per Dozen | J36: 59 | K36: =B36*J36 -> 59
B37: 1 | C37: # 67655 | D37: purple ribbons | F37: Tec 1450/1650 | I37: Per Dozen | J37: 49 | K37: =B37*J37 -> 49
B38: 1 | C38: # 67215 | D38: purple ribbons | F38: Tec RKP300 | I38: Per Dozen | J38: 39 | K38: =B38*J38 -> 39
B39: 1 | C39: # 62285 | D39: purple ribbons | F39: Tec MA1350 | I39: Per Dozen | J39: 39 | K39: =B39*J39 -> 39
B40: 1 | C40: # 62240 | D40: purple ribbons | F40: Epson 30/34/38 | I40: Per Dozen | J40: 52 | K40: 52
B41: 1 | C41: # 62235 | D41: black ribbons | F41: Epson 30/34/38 | I41: Per Dozen | J41: 52 | K41: =B41*J41 -> 52
B42: 1 | C42: # 62225 | D42: purple ribbons | F42: Tec DRS207 | I42: Per Dozen | J42: 39 | K42: =B42*J42 -> 39
B44: 1 | C44: # 62-199 | D44: POS ribbon/ink | F44: Other | I44: Per Dozen | J44: 39 | K44: =B44*J44 -> 39
B45: 1 | C45: # 62-198 | D45: POS ribbon/ink | F45: Other | I45: each | J45: 7.5 | K45: =B45*J45 -> 7.5
B46: 1 | C46: # 62-197 | D46: Office Printer Toner | I46: each | J46: 55 | K46: =B46*J46 -> 55
B47: 1 | C47: # 62-196 | D47: Office Printer Drum | I47: each | J47: 45 | K47: =B47*J47 -> 45
B50: LABELS
B51: 1 | C51: # 1612-B | D51: Tec Sl9000/SL5300 | F51: continuous | I51: case | J51: 75 | K51: =B51*J51 -> 75
B52: 1 | C52: # 1681 | D52: Tec Sl9000/SL5300 | F52: 57mm x 49.2 mm | H52: UPC | I52: case | J52: 75 | K52: =B52*J52 -> 75
B53: 1 | C53: # 1478 | D53: Cas | F53: 58mm x 60mm | H53: S/H | I53: case | J53: 65 | K53: =B53*J53 -> 65
B54: 1 | C54: # 1493 | D54: Cas | F54: 58mm x 40 mm | I54: case | J54: 65 | K54: =B54*J54 -> 65
B55: 1 | C55: # 1477 | D55: Cas | F55: 58mm x 60mm | H55: Ingredient | I55: case | J55: 65 | K55: =B55*J55 -> 65
B56: 1 | C56: # 1433B | D56: Berkel 65mm | F56: Scale Labels | I56: case | J56: 75 | K56: =B56*J56 -> 75
B57: 1 | C57: # 1850-b | D57: Kilotech | F57: (10 cas min order… 4 week ETA) | I57: case | J57: 150 | K57: =B57*J57 -> 150
B58: 1 | C58: # 1909 | D58: Hobart- Quantum | F58: 1.75" | H58: 1600/roll | I58: case | J58: 175 | K58: =B58*J58 -> 175
B59: 1 | C59: # 1911 | D59: Hobart- Quantum | F59: 3" | H59: 1000/roll | I59: case | J59: 175 | K59: =B59*J59 -> 175
B61: 1 | C61: # 61-620 | D61: # Shelf Tag Labels 3" x 1" | F61: 3" x 1" | I61: per roll | J61: 9.95 | K61: =B61*J61 -> 9.95
B62: 1 | C62: # 61-630 | D62: # Shelf Tag -Godex 2.25" x 1.25" | F62: 3" x 1" | I62: per roll | J62: 19.5 | K62: =B62*J62 -> 19.5
B63: 1 | C63: # 61-640 | D63: # MaxStick | F63: 3 1/8" x 240ft | I63: per roll | J63: 19.5 | K63: =B63*J63 -> 19.5
B64: 1 | C64: # 61-670 | D64: Datamax- Direct Thermal | I64: per roll | J64: 75 | K64: =B64*J64 -> 75
B66: SUPPLY MISC
B67: 1 | C67: # 71-100 | D67: Server Swipe Card | I67: ea | J67: 2.5 | K67: =B67*J67 -> 2.5
B68: 1 | C68: # 71-200 | D68: Manager Swipe card | I68: ea | J68: 2.5 | K68: =B68*J68 -> 2.5
B69: 1 | C69: # 71-300 | D69: Retractable reel & plastic holder for Swipe card | I69: ea | J69: 5 | K69: =B69*J69 -> 5
B70: 1 | C70: # 71-400 | D70: MSR cleaner card | I70: ea | J70: 1.5 | K70: =B70*J70 -> 1.5
B71: 1 | C71: # 71-500 | D71: Thermal Printer Cleaner Card | I71: ea | J71: 1.5 | K71: =B71*J71 -> 1.5
B72: 1 | C72: # 71-600 | D72: Thermal Head Cleaner Pen | I72: ea | J72: 4.75 | K72: =B72*J72 -> 4.75
B73: 1 | C73: # 71-700 | D73: Compressed Gas Cleaner can | I73: ea | J73: 15 | K73: =B73*J73 -> 15
B74: 1 | C74: # 71-800 | D74: Hand Sanitizer- jar | I74: ea | J74: 5 | K74: =B74*J74 -> 5
B76: 1 | C76: # 71-900 | D76: Supply Item | F76: Other | I76: ea | J76: 25 | K76: =B76*J76 -> 25
B78: 1 | C78: # 72-100 | D78: Cash Drawer Till | I78: ea | J78: 55 | K78: =B78*J78 -> 55
B79: 1 | C79: # 72-150 | D79: Cash Drawer Till- reconditioned | I79: ea | J79: 25 | K79: =B79*J79 -> 25
B81: 1 | C81: # 72-200 | D81: Silicon protective KB cover- Cash reg | I81: ea | J81: 45 | K81: =B81*J81 -> 45
B82: 1 | C82: # 72-220 | D82: Silicon protective screen cover- WS | I82: ea | J82: 50 | K82: =B82*J82 -> 50
B83: 1 | C83: # 72-250 | D83: Silicon protective cover- Pay station | I83: ea | J83: 50 | K83: =B83*J83 -> 50
B85: FREIGHT | D85: per box
B86: 1 | C86: # 80-100 | D86: Ground Shipping- Zone 1 | I86: per box | J86: 15.56 | K86: =B86*J86 -> 15.56
B87: 1 | C87: # 80-110 | D87: Ground Shipping- Zone 2 | I87: per box | J87: 17.5 | K87: =B87*J87 -> 17.5
B88: 1 | C88: # 80-120 | D88: Ground Shipping- Zone 3 | I88: per box | J88: 25 | K88: =B88*J88 -> 25
B89: 1 | C89: # 80-130 | D89: Ground Shipping- Zone 4 | I89: per box | J89: 45 | K89: =B89*J89 -> 45
B90: 1 | C90: # 80-140 | D90: Overnight Shipping- up to 5 pound | I90: per box | J90: 50 | K90: =B90*J90 -> 50
B91: 1 | C91: # 80-150 | D91: Overnight Shipping- up to 15 pound | I91: per box | J91: 75 | K91: =B91*J91 -> 75
B92: 1 | C92: # 80-160 | D92: Overnight Shipping- up to 30 pound | I92: per box | J92: 125 | K92: =B92*J92 -> 125
B94: WORKSTATIONS
B95: 1 | C95: # 30-100 | D95: POS workstation- Windows | I95: ea | J95: 1695 | K95: =B95*J95 -> 1695
B96: 1 | C96: # 30-101 | D96: POS workstation- Embedded | I96: ea | J96: 1295 | K96: =B96*J96 -> 1295
B97: 1 | C97: # 30-103 | D97: POS workstation- Rear Display 2 x 20 | I97: ea | J97: 175 | K97: =B97*J97 -> 175
B98: 1 | C98: # 30-104 | D98: POS workstation- Pole Display 2x20 | I98: ea | J98: 225 | K98: =B98*J98 -> 225
B99: 1 | C99: # 30-105 | D99: POS workstation- Multi-Line Display | I99: ea | J99: 495 | K99: =B99*J99 -> 495
B101: 1 | C101: # 30-108 | D101: POS workstation- Windows- reconditioned | I101: ea | J101: 795 | K101: =B101*J101 -> 795
B102: 1 | C102: # 30-109 | D102: POS workstation- Embedded- reconditioned | I102: ea | J102: 695 | K102: =B102*J102 -> 695
B103: TABLETS
B104: 1 | C104: # 30-110 | D104: POS Tablet- Windows | I104: ea | J104: 1250 | K104: =B104*J104 -> 1250
B105: 1 | C105: # 30-111 | D105: POS Tablet- Android/non-Windows | I105: ea | J105: 1150 | K105: =B105*J105 -> 1150
B106: 1 | C106: # 30-112 | D106: POS Tablet- add scanner | I106: ea | J106: 275 | K106: =B106*J106 -> 275
B107: 1 | C107: # 30-113 | D107: POS Tablet- Charging Dock | I107: ea | J107: 275 | K107: =B107*J107 -> 275
B108: 1 | C108: # 30-114 | D108: POS Tablet- Charger | I108: ea | J108: 175 | K108: =B108*J108 -> 175
B110: 1 | C110: # 30-118 | D110: POS Tablet- Windows- reconditioned | I110: ea | J110: 695 | K110: =B110*J110 -> 695
B111: 1 | C111: # 30-119 | D111: POS Tablet- Android/non-Windows- reconditioned | I111: ea | J111: 595 | K111: =B111*J111 -> 595
B112: SOFTWARE
B113: 1 | C113: # 30-120 | D113: POS Software- NCC | I113: per WS | J113: 795 | K113: =B113*J113 -> 795
B114: 1 | C114: # 30-121 | D114: POS Software- SAM4S | I114: per WS | J114: 795 | K114: =B114*J114 -> 795
B115: 1 | C115: # 30-122 | D115: POS Software- Microsale | I115: per WS | J115: 900 | K115: =B115*J115 -> 900
B116: 1 | C116: # 30-123 | D116: POS Software- Maitre'd- addon | I116: per WS | J116: 1200 | K116: =B116*J116 -> 1200
B117: 1 | C117: # 30-124 | D117: POS Software- Maitre'd- new system | I117: per month | J117: 299 | K117: =B117*J117 -> 299
B118: 1 | C118: # 30-125 | D118: POS Software | F118: Other | I118: per WS | J118: 795 | K118: =B118*J118 -> 795
B120: 1 | C120: # 30-126 | D120: POS Software- Upgrade | I120: per WS | J120: 250 | K120: =B120*J120 -> 250
...

Sheet EMPLOYEES
A1: Performance POS 415-451-4861 100-A Pelican Way, San Rafael CA 94901
A2: Toll-Free Support: 888-411-3375 support@performancepos.com
A4: Employee | C4: Ext | D4: Desk | E4: Cell | F4: Email
A6: Antonio Hudnall | B6: AH | C6: 112 | D6: 415-720-8345 | E6: 415-532-6834 | F6: antonio@performancepos.com
A7: Austen | E7: 515-337-3309
A8: Mo | E8: 650-242-6487
A9: Rick Villasin | E9: 415-203-9112
A10: Denny Deyerle | B10: DD | C10: 110 | D10: 415-755-3512 | E10: 209-801-2674 | F10: denny@performancepos.com
A11: Doug Kelly | B11: DK | C11: 102 | D11: 415-521-0979 | E11: 415-432-0630 | F11: dougkelly@performancepos.com
A12: Eltjon Lala | B12: EL | C12: 108 | D12: 415-755-0408 | E12: 978-608-3975 | F12: eltjon@performancepos.com
A13: Ernesto | E13: 415-706-5775
A14: Jose Santos | B14: JS | C14: 109 | D14: 415-755-0111 | E14: 415-747-2564 | F14: josesantos@performancepos.com
A15: Josue | E15: 510-480-5415
A16: Lowell Galang | B16: LG | C16: 106 | D16: 415-755-5910 | E16: 650-278-2997 | F16: lgalang@performancepos.com
A17: Milton Bland | B17: MB | C17: 107 | D17: 415-755-0337 | E17: 415-747-0039 | F17: milton@performancepos.com
A18: Rich Alden | B18: RA | C18: 104 | D18: 415-521-0776 | E18: 415-747-0038 | F18: richalden@performancepos.com
A19: Rob Freaney | B19: RF | C19: 101 | D19: 415-521-0548 | E19: 415-747-2568 | F19: robfreaney@performancepos.com
A21: Outside Tech Resources
A23: Pete Pizzino | B23: PP | D23: 510-506-6316 | F23: cashreg@sbcglobal.net
A24: POS & ECR
A25: NCC & RHQ | D25: 866-944-5164 | F25: nccusa.com & nccusa.com/rhq
A26: Posera Maitre'd | D26: 888-404-2662 | F26: distributors.maitredpos.com
A27: Casio | D27: 800-633-5586 | F27: casio.com
A28: Credit Cards
A29: Datacap | D29: 215-997-8989 | F29: datacapsystems.com
A30: Mercury Vantiv | D30: 800-846-4472 | F30: techsupport@mercurypay.com
A31: Sterling | D31: 800-591-6098 | F31: sterlingpayment.com
